QuranAPI/__init__.py
QuranAPI-1.5.dist-info/LICENSE.txt
QuranAPI-1.5.dist-info/METADATA
QuranAPI-1.5.dist-info/WHEEL
QuranAPI-1.5.dist-info/top_level.txt
QuranAPI-1.5.dist-info/RECORD
