Metadata-Version: 2.1
Name: QuranAPI
Version: 1.5
Summary: Get Quran verses specifically or even randomly! Alongside the Quran we also provide prayer times thanks to Aladhan!
Home-page: https://github.com/zacharierrr/QuranAPI/
Author: nooby xviii
Author-email: xviii2008@gmail.com
License: UNKNOWN
Platform: UNKNOWN
Classifier: Programming Language :: Python :: 3
Classifier: License :: OSI Approved :: MIT License
Classifier: Operating System :: OS Independent
Requires-Python: >=3.7
Requires-Dist: aiohttp
